[
  {
    "name": "Grayson Rodriguez",
    "team": "Detroit Tigers @ Los Angeles Angels",
    "line": 15.5,
    "under": -130,
    "book": "BetMGM",
    "proj": 12.5,
    "edge": 23,
    "pUnder": 79,
    "siera": 5.032762779392477,
    "tag": "both",
    "bet": true
  },
  {
    "name": "Bryan Woo",
    "team": "San Francisco Giants @ Seattle Mariners",
    "line": 17.5,
    "under": 146,
    "book": "FanDuel",
    "proj": 17.5,
    "edge": 9,
    "pUnder": 50,
    "siera": 3.628222841239033,
    "tag": null,
    "bet": false
  },
  {
    "name": "JT Ginn",
    "team": "Washington Nationals @ Athletics",
    "line": 15.5,
    "under": -153,
    "book": "DraftKings",
    "proj": 15.1,
    "edge": -7,
    "pUnder": 54,
    "siera": 4.4983223749031245,
    "tag": null,
    "bet": false
  },
  {
    "name": "Logan Webb",
    "team": "San Francisco Giants @ Seattle Mariners",
    "line": 18.5,
    "under": -135,
    "book": "BetMGM",
    "proj": 19.2,
    "edge": -14,
    "pUnder": 44,
    "siera": 4.003402400979098,
    "tag": null,
    "bet": false
  },
  {
    "name": "Tarik Skubal",
    "team": "Detroit Tigers @ Los Angeles Angels",
    "line": 18.5,
    "under": -189,
    "book": "DraftKings",
    "proj": 18.5,
    "edge": -15,
    "pUnder": 50,
    "siera": 2.696155980028643,
    "tag": null,
    "bet": false
  }
]