[
  {
    "name": "Ryan Weathers",
    "team": "Pittsburgh Pirates @ New York Yankees",
    "opp": "Pittsburgh Pirates",
    "line": 17.5,
    "under": -125,
    "book": "Bovada",
    "proj": 16,
    "edge": 8,
    "pUnder": 63,
    "siera": 3.477407950112784,
    "tag": null,
    "bet": false
  },
  {
    "name": "Tanner Bibee",
    "team": "Minnesota Twins @ Cleveland Guardians",
    "opp": "Minnesota Twins",
    "line": 17.5,
    "under": 100,
    "book": "Bovada",
    "proj": 16.8,
    "edge": 7,
    "pUnder": 57,
    "siera": 4.358942054145419,
    "tag": null,
    "bet": false
  },
  {
    "name": "Emmet Sheehan",
    "team": "Los Angeles Dodgers @ Philadelphia Phillies",
    "opp": "Philadelphia Phillies",
    "line": 15.5,
    "under": -115,
    "book": "Bovada",
    "proj": 14.8,
    "edge": 4,
    "pUnder": 57,
    "siera": 3.7176806522099994,
    "tag": null,
    "bet": false
  },
  {
    "name": "Shane Baz",
    "team": "Baltimore Orioles @ Boston Red Sox",
    "opp": "Boston Red Sox",
    "line": 17.5,
    "under": -115,
    "book": "Bovada",
    "proj": 17.3,
    "edge": -1,
    "pUnder": 53,
    "siera": 4.62490886317244,
    "tag": null,
    "bet": false
  },
  {
    "name": "Dylan Cease",
    "team": "Tampa Bay Rays @ Toronto Blue Jays",
    "opp": "Tampa Bay Rays",
    "line": 17.5,
    "under": 130,
    "book": "Bovada",
    "proj": 18.3,
    "edge": -3,
    "pUnder": 40,
    "siera": 2.963050187718382,
    "tag": null,
    "bet": false
  },
  {
    "name": "Joe Ryan",
    "team": "Minnesota Twins @ Cleveland Guardians",
    "opp": "Cleveland Guardians",
    "line": 18.5,
    "under": -165,
    "book": "Bovada",
    "proj": 17.8,
    "edge": -6,
    "pUnder": 56,
    "siera": 3.186155308085894,
    "tag": null,
    "bet": false
  },
  {
    "name": "Braxton Ashcraft",
    "team": "Pittsburgh Pirates @ New York Yankees",
    "opp": "New York Yankees",
    "line": 17.5,
    "under": 105,
    "book": "Bovada",
    "proj": 18.2,
    "edge": -9,
    "pUnder": 40,
    "siera": 3.2220902246732708,
    "tag": null,
    "bet": false
  },
  {
    "name": "Nick Martinez",
    "team": "Tampa Bay Rays @ Toronto Blue Jays",
    "opp": "Toronto Blue Jays",
    "line": 16.5,
    "under": -105,
    "book": "Bovada",
    "proj": 17.2,
    "edge": -10,
    "pUnder": 41,
    "siera": 4.76155079005412,
    "tag": null,
    "bet": false
  },
  {
    "name": "Payton Tolle",
    "team": "Baltimore Orioles @ Boston Red Sox",
    "opp": "Baltimore Orioles",
    "line": 15.5,
    "under": -120,
    "book": "Bovada",
    "proj": 16.6,
    "edge": -16,
    "pUnder": 39,
    "siera": 3.9324372965162975,
    "tag": null,
    "bet": false
  },
  {
    "name": "Cristopher Sanchez",
    "team": "Los Angeles Dodgers @ Philadelphia Phillies",
    "opp": "Los Angeles Dodgers",
    "line": 18.5,
    "under": -140,
    "book": "Bovada",
    "proj": 19.5,
    "edge": -19,
    "pUnder": 40,
    "siera": 2.8448019890638605,
    "tag": null,
    "bet": false
  }
]